unified_map/__init__.py
unified_map/cluster_setup.py
unified_map/multivariate/__init__.py
unified_map/multivariate/distributed.py
unified_map/multivariate/parallel.py
unified_map/multivariate/serial.py
unified_map/univariate/__init__.py
unified_map/univariate/distributed.py
unified_map/univariate/parallel.py
unified_map/univariate/serial.py
unified_map-1.0.0.dist-info/METADATA
unified_map-1.0.0.dist-info/RECORD
unified_map-1.0.0.dist-info/WHEEL
unified_map-1.0.0.dist-info/top_level.txt
