Metadata-Version: 2.1
Name: unified-map
Version: 1.0.0
Summary: Apply a function to a list of arguments and collect the results – serial, parallel or distributed.
Home-page: https://github.com/robert-haas/unified-map
Author: Robert Haas
Author-email: robert.haas@protonmail.com
License: Apache License, Version 2.0
Keywords: map,parallel map,parallel for,embarrassingly parallel,perfectly parallel,pleasingly parallel,parallel computing,distributed computing
Platform: UNKNOWN
Classifier: Development Status :: 5 - Production/Stable
Classifier: Intended Audience :: Developers
Classifier: Intended Audience :: Science/Research
Classifier: License :: OSI Approved :: Apache Software License
Classifier: Natural Language :: English
Classifier: Operating System :: OS Independent
Classifier: Programming Language :: Python :: 3
Classifier: Programming Language :: Python :: 3.5
Classifier: Programming Language :: Python :: 3.6
Classifier: Programming Language :: Python :: 3.7
Classifier: Topic :: Utilities
Requires-Python: >=3.5
Provides-Extra: complete
Provides-Extra: dev
Provides-Extra: complete
Requires-Dist: dask[complete]; extra == 'complete'
Requires-Dist: joblib; extra == 'complete'
Provides-Extra: dev
Requires-Dist: dask[complete]; extra == 'dev'
Requires-Dist: joblib; extra == 'dev'
Requires-Dist: pytest; extra == 'dev'
Requires-Dist: pytest-benchmark; extra == 'dev'
Requires-Dist: pytest-cov; extra == 'dev'
Requires-Dist: sphinx; extra == 'dev'
Requires-Dist: sphinx-rtd-theme; extra == 'dev'
